pip_name_generator/__init__.py
pip_name_generator-2025.9.101449.dist-info/licenses/LICENSE
pip_name_generator-2025.9.101449.dist-info/METADATA
pip_name_generator-2025.9.101449.dist-info/WHEEL
pip_name_generator-2025.9.101449.dist-info/top_level.txt
pip_name_generator-2025.9.101449.dist-info/RECORD
