Metadata-Version: 2.4
Name: pip_name_generator
Version: 2025.9.101449
Home-page: https://github.com/chigwell/pip_name_generator
Author: Eugene Evstafev
Author-email: hi@eugene.plus
License: MIT
Classifier: License :: OSI Approved :: MIT License
Classifier: Development Status :: 3 - Alpha
Classifier: Intended Audience :: Developers
Classifier: Programming Language :: Python :: 3
Classifier: Operating System :: OS Independent
Requires-Python: >=3.6
License-File: LICENSE
Requires-Dist: requests>=2.20.0
Requires-Dist: langchain_llm7
Requires-Dist: llmatch_messages
Requires-Dist: langchain_core
Dynamic: author
Dynamic: author-email
Dynamic: classifier
Dynamic: description
Dynamic: description-content-type
Dynamic: home-page
Dynamic: license
Dynamic: license-file
Dynamic: requires-dist
Dynamic: requires-python
